ignoregen/__init__.py
ignoregen/cli.py
ignoregen/core.py
ignoregen/detector.py
ignoregen/utils.py
ignoregen/templates/__init__.py
ignoregen/templates/base.py
ignoregen/templates/cpp.py
ignoregen/templates/django.py
ignoregen/templates/java.py
ignoregen/templates/nodejs.py
ignoregen/templates/python.py
ignoregen/templates/react.py
ignoregen_cli-1.0.0.dist-info/licenses/LICENSE
tests/__init__.py
tests/test_cli.py
tests/test_core.py
tests/test_detector.py
ignoregen_cli-1.0.0.dist-info/METADATA
ignoregen_cli-1.0.0.dist-info/WHEEL
ignoregen_cli-1.0.0.dist-info/entry_points.txt
ignoregen_cli-1.0.0.dist-info/top_level.txt
ignoregen_cli-1.0.0.dist-info/RECORD
