Metadata-Version: 2.4
Name: ignoregen-cli
Version: 1.0.0
Summary: A CLI tool and Python package for generating .gitignore files
Home-page: https://github.com/victorabimbola/ignoregen
Author: Victor Abimbola
Author-email: Victor Abimbola <abimbolaolawale41@gmail.com>
License-Expression: MIT
Project-URL: Homepage, https://github.com/victorabimbola/ignoregen
Project-URL: Repository, https://github.com/victorabimbola/ignoregen
Project-URL: Issues, https://github.com/victorabimbola/ignoregen/issues
Classifier: Development Status :: 5 - Production/Stable
Classifier: Intended Audience :: Developers
Classifier: Operating System :: OS Independent
Classifier: Programming Language :: Python :: 3
Classifier: Topic :: Utilities
Requires-Python: >=3.7
License-File: LICENSE
Dynamic: author
Dynamic: home-page
Dynamic: license-file
Dynamic: requires-python
